pyarmor/man/__init__.py
pyarmor/man/default.cfg
pyarmor/man/navigate.py
pyarmor/man/report.py
pyarmor/man/shell.py
pyarmor/man/solution.py
pyarmor/man/util.py
pyarmor/man/assets/en/README.rst
pyarmor/man/assets/en/report.html
pyarmor/man/assets/en/examples/index.html
pyarmor/man/assets/en/learn/commands.html
pyarmor/man/assets/en/learn/features.html
pyarmor/man/assets/en/learn/index.html
pyarmor/man/assets/zh/README.rst
pyarmor/man/assets/zh/report.html
pyarmor/man/assets/zh/examples/index.html
pyarmor/man/assets/zh/learn/commands.html
pyarmor/man/assets/zh/learn/features.html
pyarmor/man/assets/zh/learn/index.html
pyarmor/man/locale/en_US/LC_MESSAGES/pyarmor.mo
pyarmor/man/locale/zh_CN/LC_MESSAGES/pyarmor.mo
pyarmor.man-0.2.dist-info/METADATA
pyarmor.man-0.2.dist-info/WHEEL
pyarmor.man-0.2.dist-info/entry_points.txt
pyarmor.man-0.2.dist-info/top_level.txt
pyarmor.man-0.2.dist-info/RECORD
