Metadata-Version: 2.1
Name: pyarmor.man
Version: 0.2
Summary: A help system to learn and use Pyarmor, ask questions and report issues
Author-email: Jondy Zhao <pyarmor@163.com>
License: Free To Use But Restricted
Project-URL: Homepage, https://github.com/dashingsoft/pyarmor
Classifier: Programming Language :: Python :: 3
Classifier: License :: Free To Use But Restricted
Classifier: Operating System :: MacOS
Classifier: Operating System :: Microsoft :: Windows
Classifier: Operating System :: POSIX
Classifier: Intended Audience :: Developers
Classifier: Topic :: Software Development :: Build Tools
Classifier: Topic :: Utilities
Classifier: Topic :: Security
Classifier: Topic :: System :: Software Distribution
Requires-Python: >=3.7
